{
   "trainings": [
      {
         "correct": 12,
         "total": 32
      },
      {
         "correct": 26,
         "total": 32
      },
      {
         "correct": 32,
         "total": 32
      },
      {
         "correct": 32,
         "total": 32
      },
      {
         "correct": 32,
         "total": 32
      }
   ],
   "validations": [
      {
         "correct": 8,
         "total": 8
      },
      {
         "correct": 8,
         "total": 8
      },
      {
         "correct": 8,
         "total": 8
      },
      {
         "correct": 8,
         "total": 8
      },
      {
         "correct": 8,
         "total": 8
      }
   ]
}